fileforge/__init__.py
fileforge/__main__.py
fileforge/cli.py
fileforge/utils.py
fileforge/x_files.py
fileforge-0.1.0.dist-info/entry_points.txt
fileforge-0.1.0.dist-info/licenses/LICENSE
fileforge-0.1.0.dist-info/METADATA
fileforge-0.1.0.dist-info/WHEEL
fileforge-0.1.0.dist-info/RECORD
